cljs_loader/__init__.py
cljs_loader/loader.py
cljs_loader/utils.py
cljs_loader/templatetags/__init__.py
cljs_loader/templatetags/cljs_loader.py
django_cljs_loader-0.1.1.dist-info/DESCRIPTION.rst
django_cljs_loader-0.1.1.dist-info/METADATA
django_cljs_loader-0.1.1.dist-info/RECORD
django_cljs_loader-0.1.1.dist-info/WHEEL
django_cljs_loader-0.1.1.dist-info/metadata.json
django_cljs_loader-0.1.1.dist-info/top_level.txt
