Metadata-Version: 2.0
Name: django-cljs-loader
Version: 0.1.1
Summary: ClojureScript integration for Django
Home-page: https://github.com/jstaffans/django-cljs-loader
Author: Johannes Staffans
Author-email: johannes.staffans@gmail.com
License: UNKNOWN
Download-URL: https://github.com/jstaffans/django-cljs-loader/tarball/0.1.1
Keywords: django,clojurescript
Platform: UNKNOWN
Classifier: Programming Language :: Python :: 3.3
Classifier: Programming Language :: Python :: 3.4
Classifier: Programming Language :: Python :: 3.5
Classifier: Programming Language :: Python :: 3.6
Classifier: Framework :: Django
Classifier: Environment :: Web Environment
Classifier: License :: OSI Approved :: MIT License
Requires-Dist: edn-format (==0.5.12)
